ming_p1/__init__.py
ming_p1/simple_factory.py
ming_p1-0.1.2.dist-info/LICENSE
ming_p1-0.1.2.dist-info/WHEEL
ming_p1-0.1.2.dist-info/METADATA
ming_p1-0.1.2.dist-info/RECORD
